tensor_lib/__init__.py
tensor_lib/fns.py
tensor_lib/layers.py
tensor_lib/model.py
tensor_lib/name_manager.py
tensor_lib/ops.py
tensor_lib/util.py
tensor_lib/weight_manager.py
tensor_lib-1.8.19.dist-info/DESCRIPTION.rst
tensor_lib-1.8.19.dist-info/METADATA
tensor_lib-1.8.19.dist-info/RECORD
tensor_lib-1.8.19.dist-info/WHEEL
tensor_lib-1.8.19.dist-info/metadata.json
tensor_lib-1.8.19.dist-info/top_level.txt
