Metadata-Version: 2.0
Name: tensor-lib
Version: 1.8.19
Summary: Simplified tensorflow library
Home-page: UNKNOWN
Author: Petel__
Author-email: chunkitmax1125@gmail.com
License: UNKNOWN
Platform: UNKNOWN
Requires-Dist: numpy
